pydrivebrowser/__init__.py
pydrivebrowser/cli_browser.py
pydrivebrowser/test.py
pydrivebrowser/url_parser.py
PyDriveBrowser-0.1.0.dist-info/LICENSE
PyDriveBrowser-0.1.0.dist-info/METADATA
PyDriveBrowser-0.1.0.dist-info/WHEEL
PyDriveBrowser-0.1.0.dist-info/top_level.txt
PyDriveBrowser-0.1.0.dist-info/RECORD
