Metadata-Version: 2.1
Name: PyDriveBrowser
Version: 0.1.0
Summary: File Browser for Google Drive
Author: Basil Huber
Author-email: basil.huber@gmail.com
License: 996.ICU
Platform: UNKNOWN
License-File: LICENSE
Requires-Dist: pydrive2
Requires-Dist: pick
